{
    "Ar36": {
        "error": 0.0003104207925739693, 
        "filter_outliers_dict": {
            "filter_outliers": true, 
            "iterations": 1, 
            "std_devs": 2
        }, 
        "fit": "Linear", 
        "value": 0.0133654574916492
    }, 
    "Ar37": {
        "error": 0.010572462747702474, 
        "filter_outliers_dict": {
            "filter_outliers": true, 
            "iterations": 1, 
            "std_devs": 2
        }, 
        "fit": "linear", 
        "value": 0.026253662776031764
    }, 
    "Ar38": {
        "error": 0.004555593821306222, 
        "filter_outliers_dict": {
            "filter_outliers": true, 
            "iterations": 1, 
            "std_devs": 2
        }, 
        "fit": "linear", 
        "value": 0.004765363831095178
    }, 
    "Ar39": {
        "error": 0.012502944469872912, 
        "filter_outliers_dict": {
            "filter_outliers": true, 
            "iterations": 1, 
            "std_devs": 2
        }, 
        "fit": "Linear", 
        "value": 1.4286591337654724
    }, 
    "Ar40": {
        "error": 0.009807615222222676, 
        "filter_outliers_dict": {
            "filter_outliers": true, 
            "iterations": 1, 
            "std_devs": 2
        }, 
        "fit": "Linear", 
        "value": 8.635931322363058
    }, 
    "PM41": {
        "error": 0.0686641490431574, 
        "filter_outliers_dict": {
            "filter_outliers": false, 
            "iterations": 1, 
            "std_devs": 2
        }, 
        "fit": "linear", 
        "value": -0.1709135098291017
    }
}