{
    "Ar36": {
        "error": 0.000882457595905445,
        "filter_outliers_dict": {
            "filter_outliers": true,
            "iterations": 1,
            "std_devs": 2
        },
        "fit": "Parabolic",
        "fn": 382,
        "include_baseline_error": false,
        "n": 400,
        "reviewed": true,
        "value": 0.27850658250979743
    },
    "Ar37": {
        "error": 0.005450047842237818,
        "filter_outliers_dict": {
            "filter_outliers": true,
            "iterations": 1,
            "std_devs": 2
        },
        "fit": "Linear",
        "fn": 388,
        "include_baseline_error": false,
        "n": 400,
        "reviewed": true,
        "value": 0.021009512260901198
    },
    "Ar38": {
        "error": 0.0021562897705345793,
        "filter_outliers_dict": {
            "filter_outliers": true,
            "iterations": 1,
            "std_devs": 2
        },
        "fit": "Linear",
        "fn": 384,
        "include_baseline_error": false,
        "n": 400,
        "reviewed": true,
        "value": 0.044196370530420095
    },
    "Ar39": {
        "error": 0.008364372368133022,
        "filter_outliers_dict": {
            "filter_outliers": true,
            "iterations": 1,
            "std_devs": 2
        },
        "fit": "Parabolic",
        "fn": 384,
        "include_baseline_error": false,
        "n": 400,
        "reviewed": true,
        "value": -0.04094421098525119
    },
    "Ar40": {
        "error": 0.013236855284839004,
        "filter_outliers_dict": {
            "filter_outliers": true,
            "iterations": 1,
            "std_devs": 2
        },
        "fit": "Parabolic",
        "fn": 383,
        "include_baseline_error": false,
        "n": 400,
        "reviewed": true,
        "value": 82.02803381577225
    },
    "PM41": {
        "error": 0.06524274137032864,
        "filter_outliers_dict": {
            "filter_outliers": false,
            "iterations": 1,
            "std_devs": 2
        },
        "fit": "linear",
        "value": -0.14695487333082602
    }
}