{
    "Ar36": {
        "error": 0.0008692349894973734, 
        "filter_outliers_dict": {
            "filter_outliers": true, 
            "iterations": 1, 
            "std_devs": 2
        }, 
        "fit": "Parabolic", 
        "value": 0.27766367794131425
    }, 
    "Ar37": {
        "error": 0.004959236548336681, 
        "filter_outliers_dict": {
            "filter_outliers": true, 
            "iterations": 1, 
            "std_devs": 2
        }, 
        "fit": "linear", 
        "value": 0.026280409307451614
    }, 
    "Ar38": {
        "error": 0.0021121266462903617, 
        "filter_outliers_dict": {
            "filter_outliers": true, 
            "iterations": 1, 
            "std_devs": 2
        }, 
        "fit": "linear", 
        "value": 0.04182614388808836
    }, 
    "Ar39": {
        "error": 0.008702543422996407, 
        "filter_outliers_dict": {
            "filter_outliers": true, 
            "iterations": 1, 
            "std_devs": 2
        }, 
        "fit": "Parabolic", 
        "value": -0.02655358301770482
    }, 
    "Ar40": {
        "error": 0.012633411952632215, 
        "filter_outliers_dict": {
            "filter_outliers": true, 
            "iterations": 1, 
            "std_devs": 2
        }, 
        "fit": "Parabolic", 
        "value": 81.85424757271304
    }, 
    "PM41": {
        "error": 0.06674993697482379, 
        "filter_outliers_dict": {
            "filter_outliers": false, 
            "iterations": 1, 
            "std_devs": 2
        }, 
        "fit": "linear", 
        "value": -0.1639428290693761
    }
}