{
    "Ar36": {
        "error": 0.00021382198714942977, 
        "filter_outliers_dict": {
            "filter_outliers": true, 
            "iterations": 1, 
            "std_devs": 2
        }, 
        "fit": "Parabolic", 
        "value": 0.007933946967914357
    }, 
    "Ar37": {
        "error": 0.005503040242524027, 
        "filter_outliers_dict": {
            "filter_outliers": true, 
            "iterations": 1, 
            "std_devs": 2
        }, 
        "fit": "linear", 
        "value": 0.023927562209783097
    }, 
    "Ar38": {
        "error": 0.002053774360662905, 
        "filter_outliers_dict": {
            "filter_outliers": true, 
            "iterations": 1, 
            "std_devs": 2
        }, 
        "fit": "linear", 
        "value": -0.016722818426683515
    }, 
    "Ar39": {
        "error": 0.008004643368491606, 
        "filter_outliers_dict": {
            "filter_outliers": true, 
            "iterations": 1, 
            "std_devs": 2
        }, 
        "fit": "Parabolic", 
        "value": -0.04665450988711274
    }, 
    "Ar40": {
        "error": 0.006602388352423918, 
        "filter_outliers_dict": {
            "filter_outliers": true, 
            "iterations": 1, 
            "std_devs": 2
        }, 
        "fit": "Parabolic", 
        "value": 1.0484979752082166
    }, 
    "PM41": {
        "error": 0.06806021736118587, 
        "filter_outliers_dict": {
            "filter_outliers": false, 
            "iterations": 1, 
            "std_devs": 2
        }, 
        "fit": "linear", 
        "value": -0.17170384140106104
    }
}