{
    "AX": {
        "error": 0.007789214075751145, 
        "filter_outliers_dict": {
            "filter_outliers": true, 
            "iterations": 1, 
            "std_devs": 2
        }, 
        "fit": "average", 
        "value": -0.08422369691220931
    }, 
    "CDD": {
        "error": 3.110977948604272e-05, 
        "filter_outliers_dict": {
            "filter_outliers": true, 
            "iterations": 1, 
            "std_devs": 10
        }, 
        "fit": "average", 
        "value": 0.0003423904536667129
    }, 
    "H1": {
        "error": 0.006301328007089314, 
        "filter_outliers_dict": {
            "filter_outliers": true, 
            "iterations": 1, 
            "std_devs": 2
        }, 
        "fit": "average", 
        "value": 0.009615867241565134
    }, 
    "H2": {
        "error": 0.006342059904129424, 
        "filter_outliers_dict": {
            "filter_outliers": true, 
            "iterations": 1, 
            "std_devs": 2
        }, 
        "fit": "average", 
        "value": -0.17808145477712406
    }, 
    "L1": {
        "error": 0.0030439032273972886, 
        "filter_outliers_dict": {
            "filter_outliers": true, 
            "iterations": 1, 
            "std_devs": 2
        }, 
        "fit": "average", 
        "value": -0.019462148162358257
    }, 
    "L2": {
        "error": 0.005666481573412347, 
        "filter_outliers_dict": {
            "filter_outliers": true, 
            "iterations": 1, 
            "std_devs": 2
        }, 
        "fit": "average", 
        "value": -0.028139785769712353
    }
}