{
    "AX": {
        "error": 0.0059320527801014315, 
        "filter_outliers_dict": {
            "filter_outliers": true, 
            "iterations": 1, 
            "std_devs": 2
        }, 
        "fit": "average", 
        "value": -0.09046169191263265
    }, 
    "CDD": {
        "error": 3.6617192097748365e-05, 
        "filter_outliers_dict": {
            "filter_outliers": true, 
            "iterations": 1, 
            "std_devs": 10
        }, 
        "fit": "average", 
        "value": 0.0005780940344637977
    }, 
    "H1": {
        "error": 0.006751686866246771, 
        "filter_outliers_dict": {
            "filter_outliers": true, 
            "iterations": 1, 
            "std_devs": 2
        }, 
        "fit": "average", 
        "value": 0.02567725842021807
    }, 
    "H2": {
        "error": 0.007850671885205886, 
        "filter_outliers_dict": {
            "filter_outliers": true, 
            "iterations": 1, 
            "std_devs": 2
        }, 
        "fit": "average", 
        "value": -0.20473108535310489
    }, 
    "L1": {
        "error": 0.0028302285372247067, 
        "filter_outliers_dict": {
            "filter_outliers": true, 
            "iterations": 1, 
            "std_devs": 2
        }, 
        "fit": "average", 
        "value": -0.02720569982515501
    }, 
    "L2": {
        "error": 0.006504229098665902, 
        "filter_outliers_dict": {
            "filter_outliers": true, 
            "iterations": 1, 
            "std_devs": 2
        }, 
        "fit": "average", 
        "value": -0.02494688982820862
    }
}