{
    "AX": {
        "error": 0.007171398837215087, 
        "filter_outliers_dict": {
            "filter_outliers": true, 
            "iterations": 1, 
            "std_devs": 2
        }, 
        "fit": "average", 
        "value": -0.0923929062447535
    }, 
    "CDD": {
        "error": 2.1838467969825546e-05, 
        "filter_outliers_dict": {
            "filter_outliers": true, 
            "iterations": 1, 
            "std_devs": 10
        }, 
        "fit": "average", 
        "value": 0.00024066575132727976
    }, 
    "H1": {
        "error": 0.0051987139562136705, 
        "filter_outliers_dict": {
            "filter_outliers": true, 
            "iterations": 1, 
            "std_devs": 2
        }, 
        "fit": "average", 
        "value": -0.00020279569339465444
    }, 
    "H2": {
        "error": 0.008108172571016698, 
        "filter_outliers_dict": {
            "filter_outliers": true, 
            "iterations": 1, 
            "std_devs": 2
        }, 
        "fit": "average", 
        "value": -0.2276024558414717
    }, 
    "L1": {
        "error": 0.002882955023323327, 
        "filter_outliers_dict": {
            "filter_outliers": true, 
            "iterations": 1, 
            "std_devs": 2
        }, 
        "fit": "average", 
        "value": -0.025396713490525274
    }, 
    "L2": {
        "error": 0.006059013332058547, 
        "filter_outliers_dict": {
            "filter_outliers": true, 
            "iterations": 1, 
            "std_devs": 2
        }, 
        "fit": "average", 
        "value": -0.022569126079560266
    }
}